{
  "kind": "collectionType",
  "collectionName": "quem_somos_cards",
  "info": {
    "singularName": "quem-somos-card",
    "pluralName": "quem-somos-cards",
    "displayName": "027QuemSomosCard"
  },
  "options": {
    "draftAndPublish": false
  },
  "pluginOptions": {},
  "attributes": {
    "img": {
      "type": "string",
      "required": true
    },
    "alt": {
      "type": "string",
      "required": true
    },
    "texto": {
      "type": "string",
      "required": true
    },
    "titulo": {
      "type": "string"
    },
    "descricao": {
      "type": "text",
      "required": true,
      "unique": false
    },
    "texto_botao": {
      "type": "string",
      "required": true
    },
    "url_botao": {
      "type": "string",
      "required": true
    },
    "link_externo": {
      "type": "boolean",
      "default": false,
      "required": true
    }
  }
}
